azure/mgmt/migrationdiscoverysap/__init__.py
azure/mgmt/migrationdiscoverysap/_configuration.py
azure/mgmt/migrationdiscoverysap/_migration_discovery_sap_mgmt_client.py
azure/mgmt/migrationdiscoverysap/_patch.py
azure/mgmt/migrationdiscoverysap/_serialization.py
azure/mgmt/migrationdiscoverysap/_vendor.py
azure/mgmt/migrationdiscoverysap/_version.py
azure/mgmt/migrationdiscoverysap/py.typed
azure/mgmt/migrationdiscoverysap/aio/__init__.py
azure/mgmt/migrationdiscoverysap/aio/_configuration.py
azure/mgmt/migrationdiscoverysap/aio/_migration_discovery_sap_mgmt_client.py
azure/mgmt/migrationdiscoverysap/aio/_patch.py
azure/mgmt/migrationdiscoverysap/aio/operations/__init__.py
azure/mgmt/migrationdiscoverysap/aio/operations/_operations.py
azure/mgmt/migrationdiscoverysap/aio/operations/_patch.py
azure/mgmt/migrationdiscoverysap/aio/operations/_sap_discovery_sites_operations.py
azure/mgmt/migrationdiscoverysap/aio/operations/_sap_instances_operations.py
azure/mgmt/migrationdiscoverysap/aio/operations/_server_instances_operations.py
azure/mgmt/migrationdiscoverysap/models/__init__.py
azure/mgmt/migrationdiscoverysap/models/_migration_discovery_sap_mgmt_client_enums.py
azure/mgmt/migrationdiscoverysap/models/_models_py3.py
azure/mgmt/migrationdiscoverysap/models/_patch.py
azure/mgmt/migrationdiscoverysap/operations/__init__.py
azure/mgmt/migrationdiscoverysap/operations/_operations.py
azure/mgmt/migrationdiscoverysap/operations/_patch.py
azure/mgmt/migrationdiscoverysap/operations/_sap_discovery_sites_operations.py
azure/mgmt/migrationdiscoverysap/operations/_sap_instances_operations.py
azure/mgmt/migrationdiscoverysap/operations/_server_instances_operations.py
azure_mgmt_migrationdiscoverysap-1.0.0b1.dist-info/LICENSE
azure_mgmt_migrationdiscoverysap-1.0.0b1.dist-info/METADATA
azure_mgmt_migrationdiscoverysap-1.0.0b1.dist-info/WHEEL
azure_mgmt_migrationdiscoverysap-1.0.0b1.dist-info/top_level.txt
azure_mgmt_migrationdiscoverysap-1.0.0b1.dist-info/RECORD
